img_prc/__init__.py
img_prc/prc/__init__.py
img_prc/prc/comb.py
img_prc/prc/trns.py
img_prc/ut/__init__.py
img_prc/ut/chm.py
img_prc/ut/plotar.py
img_prc-0.0.3.dist-info/METADATA
img_prc-0.0.3.dist-info/WHEEL
img_prc-0.0.3.dist-info/top_level.txt
img_prc-0.0.3.dist-info/RECORD
