Metadata-Version: 2.1
Name: img-prc
Version: 0.0.3
Summary: Pacote feito para estudo 2
Home-page: https://github.com/AdieversonPro
Author: Adieverson Silva
Author-email: adieverson.pro@gmail.com
License: UNKNOWN
Platform: UNKNOWN
Requires-Python: >=3.8
Requires-Dist: matplotlib
Requires-Dist: numpy
Requires-Dist: scikit-image (>=0.16.1)
